AUTHORS.rst
CHANGELOG.rst
LICENSE
MANIFEST.in
README.rst
pypi_cli.py
setup.py
pypi_cli.egg-info/PKG-INFO
pypi_cli.egg-info/SOURCES.txt
pypi_cli.egg-info/dependency_links.txt
pypi_cli.egg-info/entry_points.txt
pypi_cli.egg-info/not-zip-safe
pypi_cli.egg-info/requires.txt
pypi_cli.egg-info/top_level.txt