Metadata-Version: 1.1
Name: pypi-cli
Version: 0.4.1
Summary: A command-line interface to the Python Package Index (PyPI).
Home-page: https://github.com/sloria/pypi-cli
Author: Steven Loria
Author-email: sloria1@gmail.com
License: Copyright 2014 Steven Loria
